src/__init__.py
src/base_config.py
src/base_factory.py
justasimpletest-0.0.0.dist-info/METADATA
justasimpletest-0.0.0.dist-info/WHEEL
justasimpletest-0.0.0.dist-info/top_level.txt
justasimpletest-0.0.0.dist-info/RECORD
